selene_core/__init__.py
selene_core/error_model.py
selene_core/headers.py
selene_core/plugin.py
selene_core/py.typed
selene_core/quantum_interface.py
selene_core/runtime.py
selene_core/simulator.py
selene_core/utility.py
selene_core/build_utils/README.md
selene_core/build_utils/__init__.py
selene_core/build_utils/planner.py
selene_core/build_utils/types.py
selene_core/build_utils/utils.py
selene_core/build_utils/builtins/__init__.py
selene_core/build_utils/builtins/helios.py
selene_core/build_utils/builtins/hugr.py
selene_core/build_utils/builtins/qir.py
selene_core/build_utils/builtins/selene.py
selene_core-0.2.4.dist-info/METADATA
selene_core-0.2.4.dist-info/WHEEL
selene_core-0.2.4.dist-info/RECORD
