Metadata-Version: 2.4
Name: selene-core
Version: 0.2.4
Summary: The core interop library for Selene python interfaces
Project-URL: homepage, https://github.com/quantinuum/selene/selene-core
Project-URL: repository, https://github.com/quantinuum/selene/selene-core
Requires-Python: >=3.10
Requires-Dist: hugr>=0.13.0
Requires-Dist: lief>=0.16.5
Requires-Dist: networkx<4,>=2.6
Requires-Dist: pydot>=4.0.0
Requires-Dist: pyyaml~=6.0
Requires-Dist: qir-qis>=0.1.1
Requires-Dist: typing-extensions>=4
Requires-Dist: ziglang~=0.13
